setup.py
knyfe/__init__.py
knyfe/knyfe.py
knyfe/perm_test.py
knyfe.egg-info/PKG-INFO
knyfe.egg-info/SOURCES.txt
knyfe.egg-info/dependency_links.txt
knyfe.egg-info/requires.txt
knyfe.egg-info/top_level.txt