Metadata-Version: 1.0
Name: knyfe
Version: 0.4.2
Summary: A utility for rapid exploration and preprocessing of datasets.
Home-page: http://maebert.github.com/knyfe
Author: Manuel Ebert
Author-email: maebert@uos.de
License: MIT License
Keywords: science,data,preprocessing
Platform: UNKNOWN
Classifier: Development Status :: 3 - Alpha
Classifier: Environment :: Console
Classifier: Intended Audience :: End Users/Desktop
Classifier: License :: OSI Approved :: MIT License
Classifier: Natural Language :: English
Classifier: Operating System :: OS Independent
Classifier: Programming Language :: Python
Classifier: Programming Language :: Python :: 2.7
